[{"connector": "sushiswap", "chain": "avalanche", "network": "avalanche", "trading_type": "AMM", "chain_type": "EVM", "wallet_address": "0x3888e8F5d73932B84A22BDA35c3a3b78A90186fc", "additional_spenders": [], "additional_prompt_values": {}}, {"connector": "uniswap", "chain": "polygon", "network": "mainnet", "trading_type": "AMM", "chain_type": "EVM", "wallet_address": "0x3888e8F5d73932B84A22BDA35c3a3b78A90186fc", "additional_spenders": [], "additional_prompt_values": {}, "tokens": "USDT"}, {"connector": "sushiswap", "chain": "polygon", "network": "mainnet", "trading_type": "AMM", "chain_type": "EVM", "wallet_address": "0x3888e8F5d73932B84A22BDA35c3a3b78A90186fc", "additional_spenders": [], "additional_prompt_values": {}}]